{
  "schema_version": "1.0",
  "schema": "yolo.lifecycle.stage_report.v1",
  "project": {
    "name": "project"
  },
  "stage": {
    "id": "acceptance",
    "sequence": 10,
    "label": "Acceptance",
    "writes_code": false
  },
  "status": "completed",
  "created_at": "2026-05-26T13:36:22.233Z",
  "updated_at": "2026-05-26T13:36:22.233Z",
  "inputs": [],
  "outputs": [],
  "decisions": [],
  "evidence": [
    {
      "path": "/Users/sippingroom/Developer/SamKimTest/scripts/yolo/data/prd/current/prd-yolo-progress-server-ui-provider-dogfood.json"
    },
    {
      "path": "/Users/sippingroom/Developer/SamKimTest/scripts/yolo/.yolo/lifecycle/run-report.json"
    },
    {
      "path": "/Users/sippingroom/Developer/SamKimTest/scripts/yolo/.yolo/state/evidence/adapters/progress-dashboard-ui-latest.json"
    }
  ],
  "blockers": [],
  "next_actions": [
    "Continue to /yolo-ship."
  ],
  "lifecycle_schema": "yolo.lifecycle.artifact.v1",
  "report": {
    "schema_version": "1.0",
    "schema": "yolo.acceptance.report.v1",
    "status": "pass",
    "code": "ACCEPTANCE_PASS",
    "summary": "Acceptance passed.",
    "generated_at": "2026-05-26T13:36:22.232Z",
    "project_root": "/Users/sippingroom/Developer/SamKimTest/scripts/yolo",
    "state_root": "/Users/sippingroom/Developer/SamKimTest/scripts/yolo/.yolo",
    "prd_path": "/Users/sippingroom/Developer/SamKimTest/scripts/yolo/data/prd/current/prd-yolo-progress-server-ui-provider-dogfood.json",
    "issue_summary": {
      "p0": 0,
      "p1": 0,
      "p2": 0,
      "human_review": 0,
      "total": 0
    },
    "issues": [],
    "resolver": {
      "schema_version": "1.0",
      "schema": "yolo.pack.resolver.v1",
      "status": "warning",
      "project_root": "/Users/sippingroom/Developer/SamKimTest/scripts/yolo",
      "state_root": "/Users/sippingroom/Developer/SamKimTest/scripts/yolo/.yolo",
      "manifest_roots": [
        "/Users/sippingroom/Developer/SamKimTest/scripts/yolo/.yolo/packs",
        "/Users/sippingroom/Developer/SamKimTest/scripts/yolo/.yolo/adapters"
      ],
      "selected": {
        "platform_adapter": {
          "id": "unknown/custom",
          "kind": "platform_adapter",
          "status": "warning",
          "reason": "No valid manifest was found; YOLO will not guess this project-specific context.",
          "capabilities": [],
          "source_path": ""
        },
        "stack_adapter": {
          "id": "unknown/custom",
          "kind": "stack_adapter",
          "status": "warning",
          "reason": "No valid manifest was found; YOLO will not guess this project-specific context.",
          "capabilities": [],
          "source_path": ""
        },
        "component_adapter": {
          "id": "unknown/custom",
          "kind": "component_adapter",
          "status": "warning",
          "reason": "No valid manifest was found; YOLO will not guess this project-specific context.",
          "capabilities": [],
          "source_path": ""
        },
        "design_reference_pack": {
          "id": "unknown/custom",
          "kind": "design_reference_pack",
          "status": "warning",
          "reason": "No valid manifest was found; YOLO will not guess this project-specific context.",
          "capabilities": [],
          "source_path": ""
        },
        "quality_rule_pack": {
          "id": "unknown/custom",
          "kind": "quality_rule_pack",
          "status": "warning",
          "reason": "No valid manifest was found; YOLO will not guess this project-specific context.",
          "capabilities": [],
          "source_path": ""
        },
        "acceptance_adapter": {
          "schema_version": "1.0",
          "schema": "yolo.manifest.v1",
          "id": "progress-dashboard-ui",
          "kind": "acceptance_adapter",
          "label": "",
          "description": "Progress dashboard UI/UX evidence adapter for YOLO self-dogfood runs.",
          "inputs": [
            "projectRoot",
            "stateRoot"
          ],
          "outputs": [
            "ui_evidence"
          ],
          "commands": [
            {
              "id": "progress-dashboard-ui-evidence",
              "command": "node bin/yolo.mjs progress-ui-evidence . --json",
              "timeout_ms": 90000,
              "evidence_path": ".yolo/state/evidence/progress-dashboard-ui/ui-evidence.json"
            }
          ],
          "evidence": [
            "screenshot",
            "runtime_log",
            "ui_contract"
          ],
          "capabilities": [
            "ui",
            "browser",
            "page_reachable",
            "critical_path_passed",
            "screenshot"
          ],
          "applies_to": [
            "ui",
            "progress-dashboard"
          ],
          "source_path": "/Users/sippingroom/Developer/SamKimTest/scripts/yolo/.yolo/adapters/progress-dashboard-ui.manifest.json"
        }
      },
      "selected_packs": [
        {
          "id": "unknown/custom",
          "kind": "design_reference_pack",
          "status": "warning",
          "reason": "No valid manifest was found; YOLO will not guess this project-specific context.",
          "capabilities": [],
          "source_path": ""
        },
        {
          "id": "unknown/custom",
          "kind": "quality_rule_pack",
          "status": "warning",
          "reason": "No valid manifest was found; YOLO will not guess this project-specific context.",
          "capabilities": [],
          "source_path": ""
        }
      ],
      "selected_adapters": [
        {
          "id": "unknown/custom",
          "kind": "platform_adapter",
          "status": "warning",
          "reason": "No valid manifest was found; YOLO will not guess this project-specific context.",
          "capabilities": [],
          "source_path": ""
        },
        {
          "id": "unknown/custom",
          "kind": "stack_adapter",
          "status": "warning",
          "reason": "No valid manifest was found; YOLO will not guess this project-specific context.",
          "capabilities": [],
          "source_path": ""
        },
        {
          "id": "unknown/custom",
          "kind": "component_adapter",
          "status": "warning",
          "reason": "No valid manifest was found; YOLO will not guess this project-specific context.",
          "capabilities": [],
          "source_path": ""
        },
        {
          "schema_version": "1.0",
          "schema": "yolo.manifest.v1",
          "id": "progress-dashboard-ui",
          "kind": "acceptance_adapter",
          "label": "",
          "description": "Progress dashboard UI/UX evidence adapter for YOLO self-dogfood runs.",
          "inputs": [
            "projectRoot",
            "stateRoot"
          ],
          "outputs": [
            "ui_evidence"
          ],
          "commands": [
            {
              "id": "progress-dashboard-ui-evidence",
              "command": "node bin/yolo.mjs progress-ui-evidence . --json",
              "timeout_ms": 90000,
              "evidence_path": ".yolo/state/evidence/progress-dashboard-ui/ui-evidence.json"
            }
          ],
          "evidence": [
            "screenshot",
            "runtime_log",
            "ui_contract"
          ],
          "capabilities": [
            "ui",
            "browser",
            "page_reachable",
            "critical_path_passed",
            "screenshot"
          ],
          "applies_to": [
            "ui",
            "progress-dashboard"
          ],
          "source_path": "/Users/sippingroom/Developer/SamKimTest/scripts/yolo/.yolo/adapters/progress-dashboard-ui.manifest.json"
        }
      ],
      "blockers": [],
      "warnings": [
        {
          "code": "RESOLVER_UNKNOWN_CONTEXT",
          "kind": "platform_adapter",
          "message": "platform_adapter resolved to unknown/custom."
        },
        {
          "code": "RESOLVER_UNKNOWN_CONTEXT",
          "kind": "stack_adapter",
          "message": "stack_adapter resolved to unknown/custom."
        },
        {
          "code": "RESOLVER_UNKNOWN_CONTEXT",
          "kind": "component_adapter",
          "message": "component_adapter resolved to unknown/custom."
        },
        {
          "code": "RESOLVER_UNKNOWN_CONTEXT",
          "kind": "design_reference_pack",
          "message": "design_reference_pack resolved to unknown/custom."
        },
        {
          "code": "RESOLVER_UNKNOWN_CONTEXT",
          "kind": "quality_rule_pack",
          "message": "quality_rule_pack resolved to unknown/custom."
        }
      ],
      "manifests": [
        {
          "path": "/Users/sippingroom/Developer/SamKimTest/scripts/yolo/.yolo/adapters/progress-dashboard-ui.manifest.json",
          "id": "progress-dashboard-ui",
          "kind": "acceptance_adapter",
          "status": "pass"
        }
      ],
      "next_actions": [
        "Continue with unknown/custom only if the user accepts missing project-specific packs."
      ]
    },
    "adapter_evidence": {
      "schema_version": "1.0",
      "schema": "yolo.adapter.evidence_collector.v1",
      "status": "pass",
      "code": "ADAPTER_EVIDENCE_COLLECTED",
      "summary": "Adapter evidence commands executed and evidence was collected.",
      "generated_at": "2026-05-26T13:35:41.452Z",
      "project_root": "/Users/sippingroom/Developer/SamKimTest/scripts/yolo",
      "state_root": "/Users/sippingroom/Developer/SamKimTest/scripts/yolo/.yolo",
      "adapter": {
        "id": "progress-dashboard-ui",
        "kind": "acceptance_adapter",
        "source_path": "/Users/sippingroom/Developer/SamKimTest/scripts/yolo/.yolo/adapters/progress-dashboard-ui.manifest.json",
        "capabilities": [
          "ui",
          "browser",
          "page_reachable",
          "critical_path_passed",
          "screenshot"
        ],
        "evidence": [
          "screenshot",
          "runtime_log",
          "ui_contract"
        ]
      },
      "commands": [
        {
          "id": "progress-dashboard-ui-evidence",
          "command": "node bin/yolo.mjs progress-ui-evidence . --json",
          "timeout_ms": 90000,
          "evidence_path": ".yolo/state/evidence/progress-dashboard-ui/ui-evidence.json"
        }
      ],
      "execution_policy": {
        "default_mode": "dry_run",
        "execute_requires": [
          "execute=true",
          "allowAdapterCommands=true"
        ],
        "cwd": "/Users/sippingroom/Developer/SamKimTest/scripts/yolo",
        "timeout_ms_default": 30000,
        "artifact_overwrite": "latest-per-adapter"
      },
      "artifact_path": "/Users/sippingroom/Developer/SamKimTest/scripts/yolo/.yolo/state/evidence/adapters/progress-dashboard-ui-latest.json",
      "artifact_file": ".yolo/state/evidence/adapters/progress-dashboard-ui-latest.json",
      "resolver": {
        "schema_version": "1.0",
        "schema": "yolo.pack.resolver.v1",
        "status": "warning",
        "project_root": "/Users/sippingroom/Developer/SamKimTest/scripts/yolo",
        "state_root": "/Users/sippingroom/Developer/SamKimTest/scripts/yolo/.yolo",
        "manifest_roots": [
          "/Users/sippingroom/Developer/SamKimTest/scripts/yolo/.yolo/packs",
          "/Users/sippingroom/Developer/SamKimTest/scripts/yolo/.yolo/adapters"
        ],
        "selected": {
          "platform_adapter": {
            "id": "unknown/custom",
            "kind": "platform_adapter",
            "status": "warning",
            "reason": "No valid manifest was found; YOLO will not guess this project-specific context.",
            "capabilities": [],
            "source_path": ""
          },
          "stack_adapter": {
            "id": "unknown/custom",
            "kind": "stack_adapter",
            "status": "warning",
            "reason": "No valid manifest was found; YOLO will not guess this project-specific context.",
            "capabilities": [],
            "source_path": ""
          },
          "component_adapter": {
            "id": "unknown/custom",
            "kind": "component_adapter",
            "status": "warning",
            "reason": "No valid manifest was found; YOLO will not guess this project-specific context.",
            "capabilities": [],
            "source_path": ""
          },
          "design_reference_pack": {
            "id": "unknown/custom",
            "kind": "design_reference_pack",
            "status": "warning",
            "reason": "No valid manifest was found; YOLO will not guess this project-specific context.",
            "capabilities": [],
            "source_path": ""
          },
          "quality_rule_pack": {
            "id": "unknown/custom",
            "kind": "quality_rule_pack",
            "status": "warning",
            "reason": "No valid manifest was found; YOLO will not guess this project-specific context.",
            "capabilities": [],
            "source_path": ""
          },
          "acceptance_adapter": {
            "schema_version": "1.0",
            "schema": "yolo.manifest.v1",
            "id": "progress-dashboard-ui",
            "kind": "acceptance_adapter",
            "label": "",
            "description": "Progress dashboard UI/UX evidence adapter for YOLO self-dogfood runs.",
            "inputs": [
              "projectRoot",
              "stateRoot"
            ],
            "outputs": [
              "ui_evidence"
            ],
            "commands": [
              {
                "id": "progress-dashboard-ui-evidence",
                "command": "node bin/yolo.mjs progress-ui-evidence . --json",
                "timeout_ms": 90000,
                "evidence_path": ".yolo/state/evidence/progress-dashboard-ui/ui-evidence.json"
              }
            ],
            "evidence": [
              "screenshot",
              "runtime_log",
              "ui_contract"
            ],
            "capabilities": [
              "ui",
              "browser",
              "page_reachable",
              "critical_path_passed",
              "screenshot"
            ],
            "applies_to": [
              "ui",
              "progress-dashboard"
            ],
            "source_path": "/Users/sippingroom/Developer/SamKimTest/scripts/yolo/.yolo/adapters/progress-dashboard-ui.manifest.json"
          }
        },
        "selected_packs": [
          {
            "id": "unknown/custom",
            "kind": "design_reference_pack",
            "status": "warning",
            "reason": "No valid manifest was found; YOLO will not guess this project-specific context.",
            "capabilities": [],
            "source_path": ""
          },
          {
            "id": "unknown/custom",
            "kind": "quality_rule_pack",
            "status": "warning",
            "reason": "No valid manifest was found; YOLO will not guess this project-specific context.",
            "capabilities": [],
            "source_path": ""
          }
        ],
        "selected_adapters": [
          {
            "id": "unknown/custom",
            "kind": "platform_adapter",
            "status": "warning",
            "reason": "No valid manifest was found; YOLO will not guess this project-specific context.",
            "capabilities": [],
            "source_path": ""
          },
          {
            "id": "unknown/custom",
            "kind": "stack_adapter",
            "status": "warning",
            "reason": "No valid manifest was found; YOLO will not guess this project-specific context.",
            "capabilities": [],
            "source_path": ""
          },
          {
            "id": "unknown/custom",
            "kind": "component_adapter",
            "status": "warning",
            "reason": "No valid manifest was found; YOLO will not guess this project-specific context.",
            "capabilities": [],
            "source_path": ""
          },
          {
            "schema_version": "1.0",
            "schema": "yolo.manifest.v1",
            "id": "progress-dashboard-ui",
            "kind": "acceptance_adapter",
            "label": "",
            "description": "Progress dashboard UI/UX evidence adapter for YOLO self-dogfood runs.",
            "inputs": [
              "projectRoot",
              "stateRoot"
            ],
            "outputs": [
              "ui_evidence"
            ],
            "commands": [
              {
                "id": "progress-dashboard-ui-evidence",
                "command": "node bin/yolo.mjs progress-ui-evidence . --json",
                "timeout_ms": 90000,
                "evidence_path": ".yolo/state/evidence/progress-dashboard-ui/ui-evidence.json"
              }
            ],
            "evidence": [
              "screenshot",
              "runtime_log",
              "ui_contract"
            ],
            "capabilities": [
              "ui",
              "browser",
              "page_reachable",
              "critical_path_passed",
              "screenshot"
            ],
            "applies_to": [
              "ui",
              "progress-dashboard"
            ],
            "source_path": "/Users/sippingroom/Developer/SamKimTest/scripts/yolo/.yolo/adapters/progress-dashboard-ui.manifest.json"
          }
        ],
        "blockers": [],
        "warnings": [
          {
            "code": "RESOLVER_UNKNOWN_CONTEXT",
            "kind": "platform_adapter",
            "message": "platform_adapter resolved to unknown/custom."
          },
          {
            "code": "RESOLVER_UNKNOWN_CONTEXT",
            "kind": "stack_adapter",
            "message": "stack_adapter resolved to unknown/custom."
          },
          {
            "code": "RESOLVER_UNKNOWN_CONTEXT",
            "kind": "component_adapter",
            "message": "component_adapter resolved to unknown/custom."
          },
          {
            "code": "RESOLVER_UNKNOWN_CONTEXT",
            "kind": "design_reference_pack",
            "message": "design_reference_pack resolved to unknown/custom."
          },
          {
            "code": "RESOLVER_UNKNOWN_CONTEXT",
            "kind": "quality_rule_pack",
            "message": "quality_rule_pack resolved to unknown/custom."
          }
        ],
        "manifests": [
          {
            "path": "/Users/sippingroom/Developer/SamKimTest/scripts/yolo/.yolo/adapters/progress-dashboard-ui.manifest.json",
            "id": "progress-dashboard-ui",
            "kind": "acceptance_adapter",
            "status": "pass"
          }
        ],
        "next_actions": [
          "Continue with unknown/custom only if the user accepts missing project-specific packs."
        ]
      },
      "mode": "execute",
      "command_results": [
        {
          "id": "progress-dashboard-ui-evidence",
          "command": "node bin/yolo.mjs progress-ui-evidence . --json",
          "started_at": "2026-05-26T13:35:41.454Z",
          "finished_at": "2026-05-26T13:36:22.227Z",
          "status": "pass",
          "exit_code": 0,
          "signal": null,
          "error": null,
          "stdout": "{\n  \"schema_version\": \"1.0\",\n  \"schema\": \"yolo.progress_dashboard.ui_evidence.v1\",\n  \"status\": \"pass\",\n  \"code\": \"PROGRESS_DASHBOARD_UI_EVIDENCE_PASS\",\n  \"summary\": \"Progress dashboard UI/UX evidence passed browser-rendered responsive, state, and escaping checks.\",\n  \"generated_at\": \"2026-05-26T13:36:22.201Z\",\n  \"project_root\": \"/Users/sippingroom/Developer/SamKimTest/scripts/yolo\",\n  \"state_root\": \"/Users/sippingroom/Developer/SamKimTest/scripts/yolo/.yolo\",\n  \"evidence_kind\": \"browser_rendered_html_snapshot\",\n  \"browser_execution\": true,\n  \"browser\": {\n    \"status\": \"pass\",\n    \"chrome_path\": \"/Applications/Google Chrome.app/Contents/MacOS/Google Chrome\",\n    \"reason\": null,\n    \"screenshots\": [\n      \".yolo/state/evidence/progress-dashboard-ui/screenshots/active-light-desktop.png\",\n      \".yolo/state/evidence/progress-dashboard-ui/screenshots/active-dark-desktop.png\",\n      \".yolo/state/evidence/progress-dashboard-ui/screenshots/idle-light-mobile.png\",\n      \".yolo/state/evidence/progress-dashboard-ui/screenshots/idle-dark-mobile.png\"\n    ]\n  },\n  \"design_contract\": {\n    \"source_convention\": \"DESIGN.md + UI-SPEC.md\",\n    \"required_artifacts\": [\n      \"DESIGN.md or specs/design.md\",\n      \"UI-SPEC.md or task.ui.state_matrix\",\n      \"UI evidence artifact\"\n    ],\n    \"review_pillars\": [\n      \"copywriting\",\n      \"visuals\",\n      \"color\",\n      \"typography\",\n      \"spacing\",\n      \"experience_design\"\n    ],\n    \"quality_domains\": [\n      \"accessibility\",\n      \"touch_interaction\",\n      \"performance\",\n      \"style_selection\",\n      \"layout_responsive\",\n      \"typography_color\",\n      \"animation\",\n      \"forms_feedback\",\n      \"navigation\",\n      \"charts_data\"\n    ],\n    \"source_influences\": [\n      {\n        \"id\": \"nextlevelbuilder/ui-ux-pro-max-skill\",\n        \"role\": \"priority-ordered UI/UX quality rules\",\n        \"evidence_rule\": \"Accessibility, touch, performance, style, responsive layout, typography, animation, forms, navigation, and data must be inspectable.\"\n      },\n      {\n        \"id\": \"nexu-io/open-design\",\n        \"role\": \"local-first design system and sandboxed preview/evidence pattern\",\n        \"evidence_rule\": \"UI evidence should be generated from local project files and written back as artifacts.\"\n      },\n      {\n        \"id\": \"VoltAgent/awesome-design-md\",\n        \"role\": \"plain-text DESIGN.md design-system convention\",\n        \"evidence_rule\": \"Agents need a durable text design source, not only screenshots or chat memory.\"\n      },\n      {\n        \"id\": \"goabstract/Awesome-Design-Tools\",\n        \"role\": \"design resource taxonomy for colors, icons, information architecture, and user research\",\n        \"evidence_rule\": \"Design evidence should name the checked domains instead of relying on vague polish language.\"\n      },\n      {\n        \"id\": \"DovAmir/awesome-design-patterns\",\n        \"role\": \"architecture pattern catalog\",\n        \"evidence_rule\": \"UI evidence collectors should stay adapter-based and replaceable, not hardcoded to one tool.\"\n      }\n    ]\n  },\n  \"checks\": [\n    {\n      \"id\": \"viewport_meta\",\n      \"status\": \"pass\",\n      \"message\": \"Dashboard HTML must declare a mobile viewport.\"\n    },\n    {\n      \"id\": \"active_regions\",\n      \"status\": \"pass\",\n      \"message\": \"Active run UI must expose progress, stats, task list, review, and sidebar regions.\"\n    },\n    {\n      \"id\": \"idle_lifecycle\",\n      \"status\": \"pass\",\n      \"message\": \"Idle UI must still show lifecycle state and evidence count.\"\n    },\n    {\n      \"id\": \"responsive_css\",\n      \"status\": \"pass\",\n      \"message\": \"Dashboard must include mobile and desktop responsive rules.\"\n    },\n    {\n      \"id\": \"adaptive_theme_css\",\n      \"status\": \"pass\",\n      \"message\": \"Progress server must support system-adaptive light and dark themes, with forced theme hooks for evidence.\"\n    },\n    {\n      \"id\": \"server_html_escapes_task_data\",\n      \"status\": \"pass\",\n      \"message\": \"Server-rendered task and gate text must be escaped before entering HTML\n[truncated 8237 chars]",
          "stderr": "",
          "evidence_path": "/Users/sippingroom/Developer/SamKimTest/scripts/yolo/.yolo/state/evidence/progress-dashboard-ui/ui-evidence.json",
          "evidence_file": ".yolo/state/evidence/progress-dashboard-ui/ui-evidence.json",
          "evidence_found": true
        }
      ],
      "collected_evidence": [
        {
          "schema_version": "1.0",
          "schema": "yolo.progress_dashboard.ui_evidence.v1",
          "status": "pass",
          "code": "PROGRESS_DASHBOARD_UI_EVIDENCE_PASS",
          "summary": "Progress dashboard UI/UX evidence passed browser-rendered responsive, state, and escaping checks.",
          "generated_at": "2026-05-26T13:36:22.201Z",
          "project_root": "/Users/sippingroom/Developer/SamKimTest/scripts/yolo",
          "state_root": "/Users/sippingroom/Developer/SamKimTest/scripts/yolo/.yolo",
          "evidence_kind": "browser_rendered_html_snapshot",
          "browser_execution": true,
          "browser": {
            "status": "pass",
            "chrome_path": "/Applications/Google Chrome.app/Contents/MacOS/Google Chrome",
            "reason": null,
            "screenshots": [
              ".yolo/state/evidence/progress-dashboard-ui/screenshots/active-light-desktop.png",
              ".yolo/state/evidence/progress-dashboard-ui/screenshots/active-dark-desktop.png",
              ".yolo/state/evidence/progress-dashboard-ui/screenshots/idle-light-mobile.png",
              ".yolo/state/evidence/progress-dashboard-ui/screenshots/idle-dark-mobile.png"
            ]
          },
          "design_contract": {
            "source_convention": "DESIGN.md + UI-SPEC.md",
            "required_artifacts": [
              "DESIGN.md or specs/design.md",
              "UI-SPEC.md or task.ui.state_matrix",
              "UI evidence artifact"
            ],
            "review_pillars": [
              "copywriting",
              "visuals",
              "color",
              "typography",
              "spacing",
              "experience_design"
            ],
            "quality_domains": [
              "accessibility",
              "touch_interaction",
              "performance",
              "style_selection",
              "layout_responsive",
              "typography_color",
              "animation",
              "forms_feedback",
              "navigation",
              "charts_data"
            ],
            "source_influences": [
              {
                "id": "nextlevelbuilder/ui-ux-pro-max-skill",
                "role": "priority-ordered UI/UX quality rules",
                "evidence_rule": "Accessibility, touch, performance, style, responsive layout, typography, animation, forms, navigation, and data must be inspectable."
              },
              {
                "id": "nexu-io/open-design",
                "role": "local-first design system and sandboxed preview/evidence pattern",
                "evidence_rule": "UI evidence should be generated from local project files and written back as artifacts."
              },
              {
                "id": "VoltAgent/awesome-design-md",
                "role": "plain-text DESIGN.md design-system convention",
                "evidence_rule": "Agents need a durable text design source, not only screenshots or chat memory."
              },
              {
                "id": "goabstract/Awesome-Design-Tools",
                "role": "design resource taxonomy for colors, icons, information architecture, and user research",
                "evidence_rule": "Design evidence should name the checked domains instead of relying on vague polish language."
              },
              {
                "id": "DovAmir/awesome-design-patterns",
                "role": "architecture pattern catalog",
                "evidence_rule": "UI evidence collectors should stay adapter-based and replaceable, not hardcoded to one tool."
              }
            ]
          },
          "checks": [
            {
              "id": "viewport_meta",
              "status": "pass",
              "message": "Dashboard HTML must declare a mobile viewport."
            },
            {
              "id": "active_regions",
              "status": "pass",
              "message": "Active run UI must expose progress, stats, task list, review, and sidebar regions."
            },
            {
              "id": "idle_lifecycle",
              "status": "pass",
              "message": "Idle UI must still show lifecycle state and evidence count."
            },
            {
              "id": "responsive_css",
              "status": "pass",
              "message": "Dashboard must include mobile and desktop responsive rules."
            },
            {
              "id": "adaptive_theme_css",
              "status": "pass",
              "message": "Progress server must support system-adaptive light and dark themes, with forced theme hooks for evidence."
            },
            {
              "id": "server_html_escapes_task_data",
              "status": "pass",
              "message": "Server-rendered task and gate text must be escaped before entering HTML."
            },
            {
              "id": "client_render_escapes_task_data",
              "status": "pass",
              "message": "Client-side SSE re-render must escape task text and avoid raw selector interpolation."
            },
            {
              "id": "design_contract_shape",
              "status": "pass",
              "message": "UI/UX evidence must carry design contract, 6-pillar review, and quality-domain metadata."
            },
            {
              "id": "no_inline_task_event_handler",
              "status": "pass",
              "message": "Task data must not be able to create executable inline event handlers."
            },
            {
              "id": "browser_render_active_light_desktop",
              "status": "pass",
              "message": "Chrome headless must render desktop dashboard evidence without crashing.",
              "artifact": ".yolo/state/evidence/progress-dashboard-ui/screenshots/active-light-desktop.png",
              "file_size": 92907,
              "exit_code": 0,
              "stderr": "[64329:37104600:0526/093542.323539:ERROR:net/cert/internal/trust_store_mac.cc:807] Error parsing certificate:\nERROR: Failed normalizing string\n  tag: 19\nERROR: Failed normalizing subject\n\n[64334:37104663:0526/093542.939429:ERROR:ui/display/mac/cv_display_link_mac.mm:184] CVDisplayLinkCreateWithCGDisplay failed. CVReturn: -6670\n[64334:37104663:0526/093542.940707:ERROR:ui/display/mac/cv_display_link_mac.mm:184] CVDisplayLinkCreateWithCGDisplay failed. CVReturn: -6670\n[64334:37104663:0526/093542.940939:ERROR:ui/display/mac/cv_display_link_mac.mm:184] CVDisplayLinkCreateWithCGDisplay failed. CVReturn: -6670\n[64334:37104663:0526/093542.941104:ERROR:ui/display/mac/cv_display_link_mac.mm:184] CVDisplayLinkCreateWithCGDisplay failed. CVReturn: -6670\n[64334:37104663:0526/093543.567559:ERROR:ui/display/mac/cv_display_link_mac.mm:184] CVDisplayLinkCreateWithCGDisplay failed. CVReturn: -6670\n92907 bytes written to file /Users/sippingroom/Developer/SamKimTest/scripts/yolo/.yolo/state/evidence/progr",
              "theme": "light",
              "state": "active"
            },
            {
              "id": "browser_render_active_dark_desktop",
              "status": "pass",
              "message": "Chrome headless must render desktop dashboard evidence without crashing.",
              "artifact": ".yolo/state/evidence/progress-dashboard-ui/screenshots/active-dark-desktop.png",
              "file_size": 84362,
              "exit_code": 0,
              "stderr": "[64378:37105283:0526/093552.371710:ERROR:net/cert/internal/trust_store_mac.cc:807] Error parsing certificate:\nERROR: Failed normalizing string\n  tag: 19\nERROR: Failed normalizing subject\n\n[64382:37105336:0526/093552.898068:ERROR:ui/display/mac/cv_display_link_mac.mm:184] CVDisplayLinkCreateWithCGDisplay failed. CVReturn: -6670\n[64382:37105336:0526/093552.898899:ERROR:ui/display/mac/cv_display_link_mac.mm:184] CVDisplayLinkCreateWithCGDisplay failed. CVReturn: -6670\n[64382:37105336:0526/093552.899096:ERROR:ui/display/mac/cv_display_link_mac.mm:184] CVDisplayLinkCreateWithCGDisplay failed. CVReturn: -6670\n[64382:37105336:0526/093552.899293:ERROR:ui/display/mac/cv_display_link_mac.mm:184] CVDisplayLinkCreateWithCGDisplay failed. CVReturn: -6670\n84362 bytes written to file /Users/sippingroom/Developer/SamKimTest/scripts/yolo/.yolo/state/evidence/progress-dashboard-ui/screenshots/active-dark-desktop.png",
              "theme": "dark",
              "state": "active"
            },
            {
              "id": "browser_render_idle_light_mobile",
              "status": "pass",
              "message": "Chrome headless must render mobile dashboard evidence without crashing.",
              "artifact": ".yolo/state/evidence/progress-dashboard-ui/screenshots/idle-light-mobile.png",
              "file_size": 16819,
              "exit_code": 0,
              "stderr": "[64393:37105631:0526/093602.544533:ERROR:net/cert/internal/trust_store_mac.cc:807] Error parsing certificate:\nERROR: Failed normalizing string\n  tag: 19\nERROR: Failed normalizing subject\n\n[64397:37105686:0526/093603.097300:ERROR:ui/display/mac/cv_display_link_mac.mm:184] CVDisplayLinkCreateWithCGDisplay failed. CVReturn: -6670\n[64397:37105686:0526/093603.098215:ERROR:ui/display/mac/cv_display_link_mac.mm:184] CVDisplayLinkCreateWithCGDisplay failed. CVReturn: -6670\n[64397:37105686:0526/093603.098435:ERROR:ui/display/mac/cv_display_link_mac.mm:184] CVDisplayLinkCreateWithCGDisplay failed. CVReturn: -6670\n[64397:37105686:0526/093603.098620:ERROR:ui/display/mac/cv_display_link_mac.mm:184] CVDisplayLinkCreateWithCGDisplay failed. CVReturn: -6670\n[64397:37105686:0526/093605.070014:ERROR:gpu/command_buffer/service/shared_image/shared_image_manager.cc:386] SharedImageManager::ProduceMemory: Trying to Produce a Memory representation from a non-existent mailbox.\n[64397:37105686:0526/093605.0700",
              "theme": "light",
              "state": "idle"
            },
            {
              "id": "browser_render_idle_dark_mobile",
              "status": "pass",
              "message": "Chrome headless must render mobile dashboard evidence without crashing.",
              "artifact": ".yolo/state/evidence/progress-dashboard-ui/screenshots/idle-dark-mobile.png",
              "file_size": 15517,
              "exit_code": 0,
              "stderr": "[64424:37106018:0526/093612.497939:ERROR:net/cert/internal/trust_store_mac.cc:807] Error parsing certificate:\nERROR: Failed normalizing string\n  tag: 19\nERROR: Failed normalizing subject\n\n[64433:37106069:0526/093613.035528:ERROR:ui/display/mac/cv_display_link_mac.mm:184] CVDisplayLinkCreateWithCGDisplay failed. CVReturn: -6670\n[64433:37106069:0526/093613.038545:ERROR:ui/display/mac/cv_display_link_mac.mm:184] CVDisplayLinkCreateWithCGDisplay failed. CVReturn: -6670\n[64433:37106069:0526/093613.038788:ERROR:ui/display/mac/cv_display_link_mac.mm:184] CVDisplayLinkCreateWithCGDisplay failed. CVReturn: -6670\n[64433:37106069:0526/093613.039050:ERROR:ui/display/mac/cv_display_link_mac.mm:184] CVDisplayLinkCreateWithCGDisplay failed. CVReturn: -6670\n[64433:37106069:0526/093614.960220:ERROR:gpu/command_buffer/service/shared_image/shared_image_manager.cc:386] SharedImageManager::ProduceMemory: Trying to Produce a Memory representation from a non-existent mailbox.\n[64433:37106069:0526/093614.9602",
              "theme": "dark",
              "state": "idle"
            }
          ],
          "blockers": [],
          "artifacts": {
            "idle_html": ".yolo/state/evidence/progress-dashboard-ui/idle.html",
            "active_html": ".yolo/state/evidence/progress-dashboard-ui/active.html",
            "themed_html": [
              ".yolo/state/evidence/progress-dashboard-ui/active.light.html",
              ".yolo/state/evidence/progress-dashboard-ui/active.dark.html",
              ".yolo/state/evidence/progress-dashboard-ui/idle.light.html",
              ".yolo/state/evidence/progress-dashboard-ui/idle.dark.html"
            ],
            "evidence_json": ".yolo/state/evidence/progress-dashboard-ui/ui-evidence.json"
          },
          "ui_evidence": {
            "page_reachable": true,
            "critical_path_passed": true,
            "required_state_present": true,
            "content_overlap": false,
            "text_overflow": false,
            "runtime_errors": [],
            "screenshots": [
              ".yolo/state/evidence/progress-dashboard-ui/screenshots/active-light-desktop.png",
              ".yolo/state/evidence/progress-dashboard-ui/screenshots/active-dark-desktop.png",
              ".yolo/state/evidence/progress-dashboard-ui/screenshots/idle-light-mobile.png",
              ".yolo/state/evidence/progress-dashboard-ui/screenshots/idle-dark-mobile.png"
            ],
            "visual_artifacts": [
              ".yolo/state/evidence/progress-dashboard-ui/active.html",
              ".yolo/state/evidence/progress-dashboard-ui/idle.html",
              ".yolo/state/evidence/progress-dashboard-ui/active.light.html",
              ".yolo/state/evidence/progress-dashboard-ui/active.dark.html",
              ".yolo/state/evidence/progress-dashboard-ui/idle.light.html",
              ".yolo/state/evidence/progress-dashboard-ui/idle.dark.html",
              ".yolo/state/evidence/progress-dashboard-ui/screenshots/active-light-desktop.png",
              ".yolo/state/evidence/progress-dashboard-ui/screenshots/active-dark-desktop.png",
              ".yolo/state/evidence/progress-dashboard-ui/screenshots/idle-light-mobile.png",
              ".yolo/state/evidence/progress-dashboard-ui/screenshots/idle-dark-mobile.png"
            ],
            "responsive_viewports": [
              "mobile",
              "desktop"
            ],
            "accessibility": {
              "viewport_meta": true
            }
          },
          "next_actions": [
            "Use this evidence in /yolo-run, /yolo-check, /yolo-accept, or review."
          ]
        }
      ],
      "ui_evidence": {
        "page_reachable": true,
        "critical_path_passed": true,
        "required_state_present": true,
        "content_overlap": false,
        "text_overflow": false,
        "runtime_errors": [],
        "screenshots": [
          ".yolo/state/evidence/progress-dashboard-ui/screenshots/active-light-desktop.png",
          ".yolo/state/evidence/progress-dashboard-ui/screenshots/active-dark-desktop.png",
          ".yolo/state/evidence/progress-dashboard-ui/screenshots/idle-light-mobile.png",
          ".yolo/state/evidence/progress-dashboard-ui/screenshots/idle-dark-mobile.png"
        ],
        "visual_artifacts": [
          ".yolo/state/evidence/progress-dashboard-ui/active.html",
          ".yolo/state/evidence/progress-dashboard-ui/idle.html",
          ".yolo/state/evidence/progress-dashboard-ui/active.light.html",
          ".yolo/state/evidence/progress-dashboard-ui/active.dark.html",
          ".yolo/state/evidence/progress-dashboard-ui/idle.light.html",
          ".yolo/state/evidence/progress-dashboard-ui/idle.dark.html",
          ".yolo/state/evidence/progress-dashboard-ui/screenshots/active-light-desktop.png",
          ".yolo/state/evidence/progress-dashboard-ui/screenshots/active-dark-desktop.png",
          ".yolo/state/evidence/progress-dashboard-ui/screenshots/idle-light-mobile.png",
          ".yolo/state/evidence/progress-dashboard-ui/screenshots/idle-dark-mobile.png"
        ],
        "responsive_viewports": [
          "mobile",
          "desktop"
        ],
        "accessibility": {
          "viewport_meta": true
        }
      },
      "artifacts": [
        "/Users/sippingroom/Developer/SamKimTest/scripts/yolo/.yolo/state/evidence/adapters/progress-dashboard-ui-latest.json"
      ]
    },
    "ui": {
      "ui_task_count": 3
    },
    "artifacts": [
      "/Users/sippingroom/Developer/SamKimTest/scripts/yolo/data/prd/current/prd-yolo-progress-server-ui-provider-dogfood.json",
      "/Users/sippingroom/Developer/SamKimTest/scripts/yolo/.yolo/lifecycle/run-report.json",
      "/Users/sippingroom/Developer/SamKimTest/scripts/yolo/.yolo/state/evidence/adapters/progress-dashboard-ui-latest.json"
    ],
    "next_actions": [
      "Continue to /yolo-ship."
    ]
  }
}
